frappe_powertools/__init__.py
frappe_powertools/_docutils.py
frappe_powertools/_method_chain.py
frappe_powertools/_version.py
frappe_powertools/listeners/__init__.py
frappe_powertools/listeners/_listener_utils.py
frappe_powertools/listeners/change_listeners.py
frappe_powertools/listeners/listener_decorators.py
frappe_powertools/listeners/listener_mixins.py
frappe_powertools/pydantic/__init__.py
frappe_powertools/pydantic/schema.py
frappe_powertools-0.0.1b1.dist-info/WHEEL
frappe_powertools-0.0.1b1.dist-info/METADATA
frappe_powertools-0.0.1b1.dist-info/RECORD
