Metadata-Version: 2.3
Name: frappe-powertools
Version: 0.0.1b1
Summary: Practical utilities, decorators, and hooks for Frappe developers.
Author: Mazeed / 0xsirsaif
License: MIT
Requires-Dist: pydantic>=2.12.4
Requires-Python: >=3.10
